setup.py
tweetqueue/TweetList.py
tweetqueue/__init__.py
tweetqueue/__main__.py
tweetqueue.egg-info/PKG-INFO
tweetqueue.egg-info/SOURCES.txt
tweetqueue.egg-info/dependency_links.txt
tweetqueue.egg-info/entry_points.txt
tweetqueue.egg-info/requires.txt
tweetqueue.egg-info/top_level.txt