Metadata-Version: 1.1
Name: tweetqueue
Version: 0.1.0
Summary: A command line tool for time-delaying your tweets.
Home-page: https://github.com/billyoverton/tweetqueue
Author: Billy Overton
Author-email: billy@billyoverton.com
License: MIT License
Keywords: Twitter
Platform: UNKNOWN
Classifier: Development Status :: 3 - Alpha
Classifier: Intended Audience :: End Users/Desktop
Classifier: Topic :: Utilities
Classifier: Topic :: Communications
